scrapy_splash/__init__.py
scrapy_splash/cache.py
scrapy_splash/cookies.py
scrapy_splash/dupefilter.py
scrapy_splash/middleware.py
scrapy_splash/request.py
scrapy_splash/response.py
scrapy_splash/responsetypes.py
scrapy_splash/utils.py
scrapy_splash-0.11.0.dist-info/LICENSE.txt
scrapy_splash-0.11.0.dist-info/METADATA
scrapy_splash-0.11.0.dist-info/WHEEL
scrapy_splash-0.11.0.dist-info/top_level.txt
scrapy_splash-0.11.0.dist-info/RECORD
